README.md
setup.cfg
setup.py
pytest_mockredis/__init__.py
pytest_mockredis/plugin.py
pytest_mockredis/server.py
pytest_mockredis.egg-info/PKG-INFO
pytest_mockredis.egg-info/SOURCES.txt
pytest_mockredis.egg-info/dependency_links.txt
pytest_mockredis.egg-info/not-zip-safe
pytest_mockredis.egg-info/requires.txt
pytest_mockredis.egg-info/top_level.txt